README.rst
setup.py
Radiovy.egg-info/PKG-INFO
Radiovy.egg-info/SOURCES.txt
Radiovy.egg-info/dependency_links.txt
Radiovy.egg-info/entry_points.txt
Radiovy.egg-info/requires.txt
Radiovy.egg-info/top_level.txt
getradiourl/__init__.py
getradiourl/getradiourl.py
getradiourl/gstplayer.py
hkbase/__init__.py
hkbase/bt_normal_color.png
hkbase/bt_selected_color.png
hkbase/config.cfg
hkbase/hkbase.py
hkbase/pause.png
hkbase/play.png
radiovy/__init__.py
radiovy/radiovy.py
radiovy/files/radiovy_genres.png
radiovy/files/radiovy_stations_list.png
radiovy/files/radiovy_stations_update.png
radiovy/files/radiovy_top.png