Metadata-Version: 1.0
Name: Radiovy
Version: 1.0.1
Summary: Internet radio player on kivy GUI
Home-page: UNKNOWN
Author: Shiro Ninomiya
Author-email: shiro@snino.com
License: GPL3
Platform: UNKNOWN
